[
      {
            "id": 1,
            "author": "chiara",
            "title": "\"kmmom\"",
            "content": "\"uvhbjknlm•\"",
            "positiveVotes": 0,
            "negativeVotes": 0,
            "numComment": 0,
            "comments": "[]",
            "lastTimeReward": 0
      },
      {
            "id": 2,
            "author": "chiara",
            "title": "\"kmmom\"",
            "content": "\"uvhbjknlm•kjbnjkm,\"",
            "positiveVotes": 0,
            "negativeVotes": 0,
            "numComment": 0,
            "comments": "[]",
            "lastTimeReward": 0
      },
      {
            "id": 3,
            "author": "andrea",
            "title": "\"jnonon\"",
            "content": "\"mkmpol\"",
            "positiveVotes": 0,
            "negativeVotes": 0,
            "numComment": 0,
            "comments": "[]",
            "lastTimeReward": 0
      },
      {
            "id": 4,
            "author": "andrea",
            "title": "\"jnonon\"",
            "content": "\"mkmpolsddfwee\"",
            "positiveVotes": 0,
            "negativeVotes": 0,
            "numComment": 0,
            "comments": "[]",
            "lastTimeReward": 0
      }
]